fastlib/__init__.py
fastlib/constants.py
fastlib/contextvars.py
fastlib/db_engine.py
fastlib/enums.py
fastlib/migrate.py
fastlib/openapi.py
fastlib/py.typed
fastlib/request.py
fastlib/response.py
fastlib/router.py
fastlib/schema.py
fastlib/security.py
fastlib/cache/__init__.py
fastlib/cache/_memony_cache.py
fastlib/cache/_redis_cache.py
fastlib/cache/manager.py
fastlib/config/__init__.py
fastlib/config/_database_config.py
fastlib/config/_log_config.py
fastlib/config/_security_config.py
fastlib/config/_server_config.py
fastlib/config/base.py
fastlib/config/decorator.py
fastlib/config/loader.py
fastlib/config/manager.py
fastlib/config/registry.py
fastlib/config/utils.py
fastlib/exception/__init__.py
fastlib/exception/base.py
fastlib/exception/exception_handler.py
fastlib/exception/exception_manager.py
fastlib/i18n/__init__.py
fastlib/i18n/manager.py
fastlib/i18n/messages.py
fastlib/i18n/types.py
fastlib/i18n/utils.py
fastlib/logging/__init__.py
fastlib/logging/handlers.py
fastlib/mapper/__init__.py
fastlib/mapper/base_mapper.py
fastlib/mapper/impl/__init__.py
fastlib/mapper/impl/base_mapper_impl.py
fastlib/middleware/__init__.py
fastlib/middleware/db_session.py
fastlib/middleware/i18n.py
fastlib/middleware/jwt.py
fastlib/service/__init__.py
fastlib/service/base_service.py
fastlib/service/impl/__init__.py
fastlib/service/impl/base_service_impl.py
fastlib/stream/__init__.py
fastlib/stream/enums.py
fastlib/stream/event.py
fastlib/stream/handler.py
fastlib/stream/schema.py
fastlib/stream/sse.py
fastlib/utils/__init__.py
fastlib/utils/excel_util.py
fastlib/utils/file_util.py
fastlib/utils/http_util.py
fastlib/utils/ip_util.py
fastlib/utils/security_util.py
fastlib/utils/snowflake_util.py
fastlib/utils/str_util.py
fastlib/utils/validate_util.py
fastlib_py-0.5.0.dist-info/licenses/LICENSE
fastlib_py-0.5.0.dist-info/METADATA
fastlib_py-0.5.0.dist-info/WHEEL
fastlib_py-0.5.0.dist-info/top_level.txt
fastlib_py-0.5.0.dist-info/RECORD
